mcp_registry_cli/__init__.py
mcp_registry_cli/api.py
mcp_registry_cli/cli.py
mcp_registry_cli/interactive.py
mcp_registry_cli/interactive_main.py
mcp_registry_cli/interactive_simple.py
mcp_registry_cli/keyboard_input.py
mcp_registry_cli/simple_interactive.py
mcp_registry_cli/utils.py
mcp_registry_cli-0.3.4.dist-info/licenses/LICENSE
mcp_registry_cli-0.3.4.dist-info/METADATA
mcp_registry_cli-0.3.4.dist-info/WHEEL
mcp_registry_cli-0.3.4.dist-info/entry_points.txt
mcp_registry_cli-0.3.4.dist-info/top_level.txt
mcp_registry_cli-0.3.4.dist-info/RECORD
